[
  {
    "source": "official",
    "source_country": "KR",
    "brand": "LE LABO",
    "korean_name": "VIOLETTE30",
    "english_name": "",
    "normalized_name": "violette30",
    "product_type": "perfume",
    "product_subtype": "perfume",
    "product_url": "",
    "image_url": "https://lelabokorea-java.s3.amazonaws.com/images/skus/J1BQ01R000__PRODUCT_01--IMG_360--30VIOLETTE30-884969015.jpg",
    "price": {
      "raw": "₩458,000",
      "amount": 458000,
      "currency": "KRW"
    },
    "description": "비올렛 30은 하나의 꽃 안에 공존하는 이 모순된 아름다움에 대한 오마주입니다. 그 중심에는 드물게 발견되는, 그늘에서 자라는 희귀한 화이트 비올렛이 있죠. 맑고 투명하면서도 자유로운 이 꽃처럼 푸르른 그린 플로랄에 화이트 티, 시더우드, 가이악우드가 부드럽게 어우러집니다. 익숙하면서도 낯설고, 단순하지만 복합적인 이 향은 스스로에게 존재하는 수많은 '나'의 모습을 받아들이는 태도에 대한 성찰입니다.",
    "ingredients_raw": "",
    "notes": [
      "바이올렛",
      "아이리스",
      "머스크"
    ],
    "accords": [
      "플로럴"
    ],
    "keywords": [
      "감미로운",
      "여성스러운",
      "데이트 밤",
      "맑은",
      "봄날의 산책",
      "로맨틱한"
    ],
    "meta": {
      "release_year": null,
      "original_product_type": "향수",
      "original_country": "KR"
    },
    "volume": "50ml",
    "family": "플로럴",
    "aura_profile": {
      "플로럴": 1.0,
      "우디": 0.0,
      "오리엔탈": 0.0,
      "프레시": 0.0,
      "구르망": 0.0
    }
  },
  {
    "source": "official",
    "source_country": "KR",
    "brand": "LE LABO",
    "korean_name": "ANOTHER13",
    "english_name": "",
    "normalized_name": "another13",
    "product_type": "perfume",
    "product_subtype": "perfume",
    "product_url": "",
    "image_url": "https://lelabokorea-java.s3.amazonaws.com/images/skus/100PA13100__PRODUCT_01--IMG_360--ANOTHER13--1784397257.jpg",
    "price": {
      "raw": "₩458,000",
      "amount": 458000,
      "currency": "KRW"
    },
    "description": "어나더 13은 뇌쇄적이면서도 유니크한 암브록스 베이스 머스크 노트의 중독성 강한 묘약에 자스민, 모스 등 세심하게 선정된 성분들로 강렬함과 매혹을 더해 구성됩니다. Colette와의 콜라보레이션으로 탄생한 매혹적이고 독특한 향입니다.",
    "ingredients_raw": "",
    "notes": [
      "암브록산",
      "자스민",
      "모스",
      "암브레트 시드"
    ],
    "accords": [
      "머스키"
    ],
    "keywords": [
      "따뜻한",
      "섹시한",
      "순수한",
      "매력적인",
      "살냄새",
      "이브닝 파티",
      "특별한 기념일",
      "유혹적인"
    ],
    "meta": {
      "release_year": null,
      "original_product_type": "향수",
      "original_country": "KR"
    },
    "volume": "50ml",
    "family": "오리엔탈",
    "aura_profile": {
      "플로럴": 0.0,
      "우디": 0.0,
      "오리엔탈": 1.0,
      "프레시": 0.0,
      "구르망": 0.0
    }
  },
  {
    "source": "official",
    "source_country": "KR",
    "brand": "LE LABO",
    "korean_name": "SANTAL33",
    "english_name": "",
    "normalized_name": "santal33",
    "product_type": "perfume",
    "product_subtype": "perfume",
    "product_url": "",
    "image_url": "https://lelabokorea-java.s3.amazonaws.com/images/skus/100PS33100__PRODUCT_01--IMG_360--SANTAL33--1732047456.jpg",
    "price": {
      "raw": "₩458,000",
      "amount": 458000,
      "currency": "KRW"
    },
    "description": "상탈 33은 미 서부의 와일드한 평원에서 영감을 받아 탄생한 센슈얼한 향수입니다. 카다멈, 아이리스, 바이올렛, 암브록스에 스모키한 우드 향이 어우러져 스파이시하고, 가죽 향이 맴도는 머스크 노트를 완성합니다.",
    "ingredients_raw": "",
    "notes": [
      "샌달우드",
      "레더",
      "파피루스",
      "시더",
      "바이올렛",
      "카다멈",
      "아이리스",
      "앰버"
    ],
    "accords": [
      "우디"
    ],
    "keywords": [
      "안정감 있는",
      "차분한 회의",
      "묵직한",
      "온화한",
      "격식있는 자리",
      "세련된"
    ],
    "meta": {
      "release_year": null,
      "original_product_type": "향수",
      "original_country": "KR"
    },
    "volume": "50ml",
    "family": "우디",
    "aura_profile": {
      "플로럴": 0.0,
      "우디": 1.0,
      "오리엔탈": 0.0,
      "프레시": 0.0,
      "구르망": 0.0
    }
  },
  {
    "source": "official",
    "source_country": "KR",
    "brand": "LE LABO",
    "korean_name": "THÉNOIR29",
    "english_name": "",
    "normalized_name": "thenoir29",
    "product_type": "perfume",
    "product_subtype": "perfume",
    "product_url": "",
    "image_url": "https://lelabokorea-java.s3.amazonaws.com/images/skus/100PT29100__PRODUCT_01--IMG_360--THNOIR29--719110478.jpg",
    "price": {
      "raw": "₩458,000",
      "amount": 458000,
      "currency": "KRW"
    },
    "description": "떼 누아 29는 블랙 티 잎의 우아하고 아름다운 향에 바치는 찬가와도 같은 향수입니다. 베르가못, 무화과, 월계수잎의 밝은 느낌과, 시더우드, 베티버, 머스크의 다크함이 어우러져 깊이 있으면서도 산뜻한 반전 매력을 갖고 있습니다.",
    "ingredients_raw": "",
    "notes": [
      "블랙 티",
      "무화과",
      "베르가못",
      "시더",
      "베티버",
      "머스크"
    ],
    "accords": [
      "우디"
    ],
    "keywords": [
      "전통적인",
      "카리스마있는",
      "안정감 있는",
      "차분한 회의",
      "세련된",
      "가을 외출"
    ],
    "meta": {
      "release_year": null,
      "original_product_type": "향수",
      "original_country": "KR"
    },
    "volume": "50ml",
    "family": "우디",
    "aura_profile": {
      "플로럴": 0.0,
      "우디": 1.0,
      "오리엔탈": 0.0,
      "프레시": 0.0,
      "구르망": 0.0
    }
  },
  {
    "source": "official",
    "source_country": "KR",
    "brand": "LE LABO",
    "korean_name": "THÉMATCHA26",
    "english_name": "",
    "normalized_name": "thematcha26",
    "product_type": "perfume",
    "product_subtype": "perfume",
    "product_url": "",
    "image_url": "https://lelabokorea-java.s3.amazonaws.com/images/skus/J34901R000__Product_01--IMG_360--THMATCHA26-1938823520.jpg",
    "price": {
      "raw": "₩458,000",
      "amount": 458000,
      "currency": "KRW"
    },
    "description": "떼 마차 26은 조용한 자아의 순간을 위한 향입니다. 크리미한 무화과 노트가 스며든 마차 티 어코드는 부드러운 베티버와 시더우드를 베이스로 하며 매혹적인 비터 오렌지와 어우러져 기분 좋은 균형을 이룹니다.",
    "ingredients_raw": "",
    "notes": [
      "말차",
      "무화과",
      "베티버",
      "시더",
      "비터 오렌지"
    ],
    "accords": [
      "우디"
    ],
    "keywords": [
      "카리스마있는",
      "세련된",
      "차분한 회의",
      "격식있는 자리",
      "안정감 있는",
      "전통적인"
    ],
    "meta": {
      "release_year": null,
      "original_product_type": "향수",
      "original_country": "KR"
    },
    "volume": "50ml",
    "family": "우디",
    "aura_profile": {
      "플로럴": 0.0,
      "우디": 1.0,
      "오리엔탈": 0.0,
      "프레시": 0.0,
      "구르망": 0.0
    }
  },
  {
    "source": "official",
    "source_country": "KR",
    "brand": "LE LABO",
    "korean_name": "BERGAMOTE22",
    "english_name": "",
    "normalized_name": "bergamote22",
    "product_type": "perfume",
    "product_subtype": "perfume",
    "product_url": "",
    "image_url": "https://lelabokorea-java.s3.amazonaws.com/images/skus/100PB22100__PRODUCT_01--IMG_360--BERGAMOTE22--1383470821.jpg",
    "price": {
      "raw": "₩458,000",
      "amount": 458000,
      "currency": "KRW"
    },
    "description": "베르가못 22는 신선함, 달콤함, 그리고 센슈얼한 느낌을 모두 담은 시트러스 프레쉬 계열의 향수입니다. 페티그레인의 섬세한 플로럴 향, 자몽의 쌉싸래한 향, 앰버와 머스크의 풍성함이 어우러져 독특한 개성을 완성합니다.",
    "ingredients_raw": "",
    "notes": [
      "베르가못",
      "자몽",
      "앰버",
      "머스크",
      "베티버",
      "페티그레인",
      "바닐라",
      "오렌지 블로썸",
      "시더"
    ],
    "accords": [
      "시트러스"
    ],
    "keywords": [
      "여름 소풍",
      "활기찬",
      "시원한",
      "운동 후 리프레시",
      "깨끗한",
      "에너제틱한",
      "상쾌한"
    ],
    "meta": {
      "release_year": null,
      "original_product_type": "향수",
      "original_country": "KR"
    },
    "volume": "50ml",
    "family": "프레시",
    "aura_profile": {
      "플로럴": 0.0,
      "우디": 0.0,
      "오리엔탈": 0.0,
      "프레시": 1.0,
      "구르망": 0.0
    }
  },
  {
    "source": "official",
    "source_country": "KR",
    "brand": "LE LABO",
    "korean_name": "BAIE19",
    "english_name": "",
    "normalized_name": "baie19",
    "product_type": "perfume",
    "product_subtype": "perfume",
    "product_url": "",
    "image_url": "https://lelabokorea-java.s3.amazonaws.com/images/skus/J2K401R000__PRODUCT_01--IMG_360--BAIE19-2140360648.jpg",
    "price": {
      "raw": "₩458,000",
      "amount": 458000,
      "currency": "KRW"
    },
    "description": "베이 19는 비가 내린 뒤 물이 땅에 선사하는 상쾌하고 촉촉한 느낌인 '페트리코'를 담아냈습니다. 비에 젖은 주니퍼베리, 패출리, 초록 잎사귀들의 향이 어우러져 맑고 매력적인 분위기를 선사합니다.",
    "ingredients_raw": "",
    "notes": [
      "주니퍼 베리",
      "패출리",
      "그린 리프",
      "머스크",
      "세이지",
      "암브로시아"
    ],
    "accords": [
      "우디"
    ],
    "keywords": [
      "카리스마있는",
      "온화한",
      "안정감 있는",
      "가을 외출",
      "세련된",
      "차분한 회의"
    ],
    "meta": {
      "release_year": null,
      "original_product_type": "향수",
      "original_country": "KR"
    },
    "volume": "50ml",
    "family": "우디",
    "aura_profile": {
      "플로럴": 0.0,
      "우디": 1.0,
      "오리엔탈": 0.0,
      "프레시": 0.0,
      "구르망": 0.0
    }
  },
  {
    "source": "official",
    "source_country": "KR",
    "brand": "LE LABO",
    "korean_name": "LYS41",
    "english_name": "",
    "normalized_name": "lys41",
    "product_type": "perfume",
    "product_subtype": "perfume",
    "product_url": "",
    "image_url": "https://lelabokorea-java.s3.amazonaws.com/images/skus/100PL41100__PRODUCT_01--IMG_360--LYS41-1877854332.jpg",
    "price": {
      "raw": "₩458,000",
      "amount": 458000,
      "currency": "KRW"
    },
    "description": "리스 41은 릴리, 튜베로즈, 자스민 등 풍성한 화이트 플라워들이 어우러진 중독적인 플로럴 향입니다. 우아한 우드 향, 바닐라와 머스크가 더해져 한 번 빠지면 헤어 나올 수 없는 매력을 선사합니다.",
    "ingredients_raw": "",
    "notes": [
      "백합",
      "자스민",
      "투베로즈",
      "바닐라",
      "머스크",
      "우디 노츠"
    ],
    "accords": [
      "플로럴"
    ],
    "keywords": [
      "맑은",
      "데이트 밤",
      "감미로운",
      "결혼식 하객",
      "우아한",
      "부드러운"
    ],
    "meta": {
      "release_year": null,
      "original_product_type": "향수",
      "original_country": "KR"
    },
    "volume": "50ml",
    "family": "플로럴",
    "aura_profile": {
      "플로럴": 1.0,
      "우디": 0.0,
      "오리엔탈": 0.0,
      "프레시": 0.0,
      "구르망": 0.0
    }
  },
  {
    "source": "official",
    "source_country": "KR",
    "brand": "LE LABO",
    "korean_name": "AMBRETTE9",
    "english_name": "",
    "normalized_name": "ambrette9",
    "product_type": "perfume",
    "product_subtype": "perfume",
    "product_url": "",
    "image_url": "https://lelabokorea-java.s3.amazonaws.com/images/skus/100PA09100__PRODUCT_01--IMG_360--AMBRETTE9--955959219.jpg",
    "price": {
      "raw": "₩458,000",
      "amount": 458000,
      "currency": "KRW"
    },
    "description": "암브레트 9은 희귀한 머스크 원료인 암브레트 씨드에 사과와 배의 시트러스, 프루티한 향이 더해져 아기처럼 부드럽고 순수한 향을 완성합니다.",
    "ingredients_raw": "",
    "notes": [
      "암브레트",
      "프루티 노츠",
      "머스크",
      "알데하이드"
    ],
    "accords": [
      "머스키"
    ],
    "keywords": [
      "유혹적인",
      "겨울 밤 모임",
      "이브닝 파티",
      "섹시한",
      "살냄새",
      "감각적인",
      "따뜻한",
      "순수한"
    ],
    "meta": {
      "release_year": null,
      "original_product_type": "향수",
      "original_country": "KR"
    },
    "volume": "50ml",
    "family": "오리엔탈",
    "aura_profile": {
      "플로럴": 0.0,
      "우디": 0.0,
      "오리엔탈": 1.0,
      "프레시": 0.0,
      "구르망": 0.0
    }
  },
  {
    "source": "official",
    "source_country": "KR",
    "brand": "LE LABO",
    "korean_name": "EUCALYPTUS20",
    "english_name": "",
    "normalized_name": "eucalyptus20",
    "product_type": "perfume",
    "product_subtype": "perfume",
    "product_url": "",
    "image_url": "https://lelabokorea-java.s3.amazonaws.com/images/skus/J3FC01R000__PRODUCT_01--IMG_360--20EUCALYPTUS20-1726846733.jpg",
    "price": {
      "raw": "₩458,000",
      "amount": 458000,
      "currency": "KRW"
    },
    "description": "유칼립투스 20은 유칼립투스와 시더우드의 상쾌함이 라다넘의 따뜻한 레더리함, 머스크와 유향의 잔잔한 깊이감이 부드럽게 조화를 이루는 향입니다.",
    "ingredients_raw": "",
    "notes": [
      "유칼립투스",
      "베르가못",
      "패출리"
    ],
    "accords": [
      "우디"
    ],
    "keywords": [
      "가을 외출",
      "안정감 있는",
      "카리스마있는",
      "대담한",
      "전통적인",
      "차분한 회의"
    ],
    "meta": {
      "release_year": null,
      "original_product_type": "향수",
      "original_country": "KR"
    },
    "volume": "50ml",
    "family": "우디",
    "aura_profile": {
      "플로럴": 0.0,
      "우디": 1.0,
      "오리엔탈": 0.0,
      "프레시": 0.0,
      "구르망": 0.0
    }
  },
  {
    "source": "official",
    "source_country": "KR",
    "brand": "LE LABO",
    "korean_name": "ROSE31",
    "english_name": "",
    "normalized_name": "rose31",
    "product_type": "perfume",
    "product_subtype": "perfume",
    "product_url": "",
    "image_url": "https://lelabokorea-java.s3.amazonaws.com/images/skus/100PR31100__PRODUCT_01--IMG_360--ROSE31--1834247239.jpg",
    "price": {
      "raw": "₩458,000",
      "amount": 458000,
      "currency": "KRW"
    },
    "description": "로즈 31은 그라스 장미의 관능미에 커민, 올리바넘, 시더우드와 앰버가 더해져 따뜻하면서도 스파이시한 우디 향을 선사하는 신비로운 향입니다.",
    "ingredients_raw": "",
    "notes": [
      "로즈",
      "커민",
      "베티버",
      "시더",
      "머스크",
      "과약 우드",
      "오드",
      "올리바넘",
      "랍다넘"
    ],
    "accords": [
      "플로럴"
    ],
    "keywords": [
      "봄날의 산책",
      "데이트 밤",
      "섬세한",
      "여성스러운",
      "감미로운",
      "맑은"
    ],
    "meta": {
      "release_year": null,
      "original_product_type": "향수",
      "original_country": "KR"
    },
    "volume": "50ml",
    "family": "플로럴",
    "aura_profile": {
      "플로럴": 1.0,
      "우디": 0.0,
      "오리엔탈": 0.0,
      "프레시": 0.0,
      "구르망": 0.0
    }
  },
  {
    "source": "official",
    "source_country": "KR",
    "brand": "LE LABO",
    "korean_name": "LAVANDE31",
    "english_name": "",
    "normalized_name": "lavande31",
    "product_type": "perfume",
    "product_subtype": "perfume",
    "product_url": "",
    "image_url": "https://lelabokorea-java.s3.amazonaws.com/images/skus/J3LL01R000__PRODUCT_01--IMG_360--31LAVANDE31--2131298644.jpg",
    "price": {
      "raw": "₩458,000",
      "amount": 458000,
      "currency": "KRW"
    },
    "description": "라방드 31은 베르가못과 네롤리 에센셜 오일에 라벤더 꽃봉오리를 더해 상쾌함을 주고, 앰버와 머스크 베이스로 깨끗하면서도 유혹적인 유니크한 라벤더 향을 완성합니다.",
    "ingredients_raw": "",
    "notes": [
      "라벤더",
      "베르가못",
      "네롤리",
      "앰버",
      "머스크",
      "톤카 빈"
    ],
    "accords": [
      "플로럴"
    ],
    "keywords": [
      "감미로운",
      "섬세한",
      "결혼식 하객",
      "여성스러운",
      "데이트 밤",
      "맑은"
    ],
    "meta": {
      "release_year": null,
      "original_product_type": "향수",
      "original_country": "KR"
    },
    "volume": "50ml",
    "family": "플로럴",
    "aura_profile": {
      "플로럴": 1.0,
      "우디": 0.0,
      "오리엔탈": 0.0,
      "프레시": 0.0,
      "구르망": 0.0
    }
  },
  {
    "source": "official",
    "source_country": "KR",
    "brand": "LE LABO",
    "korean_name": "NEROLI36",
    "english_name": "",
    "normalized_name": "neroli36",
    "product_type": "perfume",
    "product_subtype": "perfume",
    "product_url": "",
    "image_url": "https://lelabokorea-java.s3.amazonaws.com/images/skus/100PN36100__PRODUCT_01--IMG_360--NEROLI36--721709652.jpg",
    "price": {
      "raw": "₩458,000",
      "amount": 458000,
      "currency": "KRW"
    },
    "description": "네롤리 36은 오렌지 블로썸의 따뜻하고 싱그러운 플로럴 향에 로즈, 머스크, 만다린 오렌지, 자스민, 바닐라가 어우러져 편안하면서도 열정적인 향을 완성합니다.",
    "ingredients_raw": "",
    "notes": [
      "네롤리",
      "오렌지 블로썸",
      "만다린 오렌지",
      "자스민",
      "로즈",
      "머스크",
      "바닐라",
      "알데하이드"
    ],
    "accords": [
      "플로럴"
    ],
    "keywords": [
      "우아한",
      "맑은",
      "부드러운",
      "봄날의 산책",
      "로맨틱한",
      "결혼식 하객"
    ],
    "meta": {
      "release_year": null,
      "original_product_type": "향수",
      "original_country": "KR"
    },
    "volume": "50ml",
    "family": "플로럴",
    "aura_profile": {
      "플로럴": 1.0,
      "우디": 0.0,
      "오리엔탈": 0.0,
      "프레시": 0.0,
      "구르망": 0.0
    }
  },
  {
    "source": "official",
    "source_country": "KR",
    "brand": "LE LABO",
    "korean_name": "FLEURD'ORANGER27",
    "english_name": "",
    "normalized_name": "fleurd oranger27",
    "product_type": "perfume",
    "product_subtype": "perfume",
    "product_url": "",
    "image_url": "https://lelabokorea-java.s3.amazonaws.com/images/skus/100PF27100__PRODUCT_01--IMG_360--FLEURDORANGER27-1488124388.jpg",
    "price": {
      "raw": "₩458,000",
      "amount": 458000,
      "currency": "KRW"
    },
    "description": "플레르 도란줴 27은 천연 오렌지 블로썸 원료에 프레쉬 플로럴, 레몬 향을 더해 우아함을 살렸으며, 머스크와 베르가못이 따뜻하고 화창한 느낌을 더해주는 센슈얼한 향입니다.",
    "ingredients_raw": "",
    "notes": [
      "오렌지 블로썸",
      "페티그레인",
      "베르가못",
      "레몬"
    ],
    "accords": [
      "플로럴"
    ],
    "keywords": [
      "결혼식 하객",
      "여성스러운",
      "섬세한",
      "데이트 밤",
      "감미로운",
      "부드러운"
    ],
    "meta": {
      "release_year": null,
      "original_product_type": "향수",
      "original_country": "KR"
    },
    "volume": "50ml",
    "family": "플로럴",
    "aura_profile": {
      "플로럴": 1.0,
      "우디": 0.0,
      "오리엔탈": 0.0,
      "프레시": 0.0,
      "구르망": 0.0
    }
  },
  {
    "source": "official",
    "source_country": "KR",
    "brand": "LE LABO",
    "korean_name": "JASMIN17",
    "english_name": "",
    "normalized_name": "jasmin17",
    "product_type": "perfume",
    "product_subtype": "perfume",
    "product_url": "",
    "image_url": "https://lelabokorea-java.s3.amazonaws.com/images/skus/100PJ17100__PRODUCT_01--IMG_360--JASMIN17--1406533069.jpg",
    "price": {
      "raw": "₩458,000",
      "amount": 458000,
      "currency": "KRW"
    },
    "description": "자스민 17은 모던하게 재해석된 독창적인 자스민 향으로, 머스크, 샌달우드, 바닐라를 더해 더욱 장엄하고 풍성한 센슈얼함을 선사합니다.",
    "ingredients_raw": "",
    "notes": [
      "자스민",
      "네롤리",
      "비터 오렌지",
      "머스크",
      "샌달우드",
      "바닐라",
      "앰버",
      "팔리산더 로즈우드"
    ],
    "accords": [
      "플로럴"
    ],
    "keywords": [
      "봄날의 산책",
      "맑은",
      "감미로운",
      "로맨틱한",
      "결혼식 하객",
      "여성스러운"
    ],
    "meta": {
      "release_year": null,
      "original_product_type": "향수",
      "original_country": "KR"
    },
    "volume": "50ml",
    "family": "플로럴",
    "aura_profile": {
      "플로럴": 1.0,
      "우디": 0.0,
      "오리엔탈": 0.0,
      "프레시": 0.0,
      "구르망": 0.0
    }
  },
  {
    "source": "official",
    "source_country": "KR",
    "brand": "LE LABO",
    "korean_name": "LABDANUM18",
    "english_name": "",
    "normalized_name": "labdanum18",
    "product_type": "perfume",
    "product_subtype": "perfume",
    "product_url": "",
    "image_url": "https://lelabokorea-java.s3.amazonaws.com/images/skus/100PL18100__PRODUCT_01--IMG_360--LABDANUM18--1127871926.jpg",
    "price": {
      "raw": "₩458,000",
      "amount": 458000,
      "currency": "KRW"
    },
    "description": "라다넘 18은 강렬한 앰버 노트에 사향과 카스토럼의 동물적인 향이 더해져 폭발적인 잠재력을 가진 수수께끼 같은 매력의 향수입니다.",
    "ingredients_raw": "",
    "notes": [
      "랍다넘",
      "바닐라",
      "시벳",
      "머스크",
      "카스토리움",
      "시나몬",
      "레진",
      "버치",
      "패출리",
      "구르잔 밤"
    ],
    "accords": [
      "앰버"
    ],
    "keywords": [
      "유혹적인",
      "따뜻한",
      "감각적인",
      "섹시한",
      "특별한 기념일",
      "겨울 밤 모임"
    ],
    "meta": {
      "release_year": null,
      "original_product_type": "향수",
      "original_country": "KR"
    },
    "volume": "50ml",
    "family": "오리엔탈",
    "aura_profile": {
      "플로럴": 0.0,
      "우디": 0.0,
      "오리엔탈": 1.0,
      "프레시": 0.0,
      "구르망": 0.0
    }
  },
  {
    "source": "official",
    "source_country": "KR",
    "brand": "LE LABO",
    "korean_name": "PATCHOULI24",
    "english_name": "",
    "normalized_name": "patchouli24",
    "product_type": "perfume",
    "product_subtype": "perfume",
    "product_url": "",
    "image_url": "https://lelabokorea-java.s3.amazonaws.com/images/skus/100PP24100__PRODUCT_01--IMG_360--PATCHOULI24-967148584.jpg",
    "price": {
      "raw": "₩458,000",
      "amount": 458000,
      "currency": "KRW"
    },
    "description": "패출리 24는 자작나무의 스모키한 가죽 향이 지배적이며, 곧이어 다가오는 바닐라 향이 야성적인 향을 부드럽고 센슈얼하게 감싸주는 위험한 매력의 향수입니다.",
    "ingredients_raw": "",
    "notes": [
      "패출리",
      "버치",
      "스티락스",
      "바닐라"
    ],
    "accords": [
      "우디"
    ],
    "keywords": [
      "가을 외출",
      "전통적인",
      "세련된",
      "격식있는 자리",
      "카리스마있는",
      "안정감 있는"
    ],
    "meta": {
      "release_year": null,
      "original_product_type": "향수",
      "original_country": "KR"
    },
    "volume": "50ml",
    "family": "우디",
    "aura_profile": {
      "플로럴": 0.0,
      "우디": 1.0,
      "오리엔탈": 0.0,
      "프레시": 0.0,
      "구르망": 0.0
    }
  },
  {
    "source": "official",
    "source_country": "KR",
    "brand": "LE LABO",
    "korean_name": "YLANG49",
    "english_name": "",
    "normalized_name": "ylang49",
    "product_type": "perfume",
    "product_subtype": "perfume",
    "product_url": "",
    "image_url": "https://lelabokorea-java.s3.amazonaws.com/images/skus/100PY49100__PRODUCT_01--IMG_360--YLANG49-806525765.jpg",
    "price": {
      "raw": "₩458,000",
      "amount": 458000,
      "currency": "KRW"
    },
    "description": "일랑 49는 시프레 플로럴 계열의 향수로, 일랑일랑에 타히티 가드니아, 패출리, 오크모스 등이 어우러져 더욱 관능적이고 센슈얼한 플로럴을 완성합니다.",
    "ingredients_raw": "",
    "notes": [
      "일랑일랑",
      "패출리",
      "오크모스",
      "가드니아",
      "샌달우드",
      "벤조인"
    ],
    "accords": [
      "플로럴"
    ],
    "keywords": [
      "섬세한",
      "부드러운",
      "맑은",
      "결혼식 하객",
      "감미로운",
      "데이트 밤"
    ],
    "meta": {
      "release_year": null,
      "original_product_type": "향수",
      "original_country": "KR"
    },
    "volume": "50ml",
    "family": "플로럴",
    "aura_profile": {
      "플로럴": 1.0,
      "우디": 0.0,
      "오리엔탈": 0.0,
      "프레시": 0.0,
      "구르망": 0.0
    }
  },
  {
    "source": "official",
    "source_country": "KR",
    "brand": "LE LABO",
    "korean_name": "TONKA25",
    "english_name": "",
    "normalized_name": "tonka25",
    "product_type": "perfume",
    "product_subtype": "perfume",
    "product_url": "",
    "image_url": "https://lelabokorea-java.s3.amazonaws.com/images/skus/100PT25100__PRODUCT_01--IMG_360--TONKA25-140793169.jpg",
    "price": {
      "raw": "₩458,000",
      "amount": 458000,
      "currency": "KRW"
    },
    "description": "통카 25는 어두우면서도 따스한 살결을 떠올리게 하는 향으로, 젖은 나무 덤불과 머스크, 바닐라의 희미한 달콤함이 아름답게 조화를 이룹니다.",
    "ingredients_raw": "",
    "notes": [
      "톤카 빈",
      "머스크",
      "시더",
      "스티락스",
      "오렌지 블로썸"
    ],
    "accords": [
      "우디"
    ],
    "keywords": [
      "가을 외출",
      "대담한",
      "묵직한",
      "격식있는 자리",
      "전통적인",
      "안정감 있는"
    ],
    "meta": {
      "release_year": null,
      "original_product_type": "향수",
      "original_country": "KR"
    },
    "volume": "50ml",
    "family": "우디",
    "aura_profile": {
      "플로럴": 0.0,
      "우디": 1.0,
      "오리엔탈": 0.0,
      "프레시": 0.0,
      "구르망": 0.0
    }
  },
  {
    "source": "official",
    "source_country": "KR",
    "brand": "LE LABO",
    "korean_name": "VETIVER46",
    "english_name": "",
    "normalized_name": "vetiver46",
    "product_type": "perfume",
    "product_subtype": "perfume",
    "product_url": "",
    "image_url": "https://lelabokorea-java.s3.amazonaws.com/images/skus/100PV46100__PRODUCT_01--IMG_360--VETIVER46-1076320394.jpg",
    "price": {
      "raw": "₩458,000",
      "amount": 458000,
      "currency": "KRW"
    },
    "description": "베티버 46은 최상급 베티버를 원료로 한 가장 남성적인 매력의 향수입니다. 페퍼, 가이악, 시더우드 등 46가지 원료와 유향이 더해져 유혹적인 잔향을 남깁니다.",
    "ingredients_raw": "",
    "notes": [
      "베티버",
      "시더",
      "올리바넘",
      "과약 우드",
      "랍다넘",
      "페퍼",
      "클로브",
      "베르가못",
      "바닐라"
    ],
    "accords": [
      "우디"
    ],
    "keywords": [
      "전통적인",
      "가을 외출",
      "세련된",
      "카리스마있는",
      "차분한 회의",
      "안정감 있는"
    ],
    "meta": {
      "release_year": null,
      "original_product_type": "향수",
      "original_country": "KR"
    },
    "volume": "50ml",
    "family": "우디",
    "aura_profile": {
      "플로럴": 0.0,
      "우디": 1.0,
      "오리엔탈": 0.0,
      "프레시": 0.0,
      "구르망": 0.0
    }
  }
]